[
  {
    "productId": "iphone_14_pro_max_512gb",
    "image": {
      "src": "/assets/iphone_14_pro_max.png",
      "altText": "IPhone image"
    },
    "price": "139 000 —",
    "fullName": "Телефон Apple iPhone 14 Pro Max 512Gb (Purple)",
    "tag": "discount"
  },
  {
    "productId": "iphone_14_pro_512gb",
    "image": {
      "src": "/assets/iphone_14_pro.png",
      "altText": "IPhone image"
    },
    "price": "129 000 —",
    "fullName": "Телефон Apple iPhone 14 Pro 512Gb (Purple)",
    "tag": "discount"
  },
  {
    "productId": "iphone_14_256gb",
    "image": {
      "src": "/assets/iphone_14.png",
      "altText": "IPhone image"
    },
    "price": "79 000 —",
    "fullName": "Телефон Apple iPhone 14 256Gb (Purple)",
    "tag": "discount"
  },
  {
    "productId": "iphone_14_pro_max_256gb",
    "image": {
      "src": "/assets/iphone_14_pro_max.png",
      "altText": "IPhone image"
    },
    "price": "119 000 —",
    "fullName": "Телефон Apple iPhone 14 Pro Max 256Gb (Purple)",
    "tag": "discount"
  },
  {
    "productId": "iphone_14_pro_256gb",
    "image": {
      "src": "/assets/iphone_14_pro.png",
      "altText": "IPhone image"
    },
    "price": "109 000 —",
    "fullName": "Телефон Apple iPhone 14 Pro 256Gb (Purple)",
    "tag": "discount"
  },
  {
    "productId": "iphone_14_128gb",
    "image": {
      "src": "/assets/iphone_14.png",
      "altText": "IPhone image"
    },
    "price": "69 000 —",
    "fullName": "Телефон Apple iPhone 14 128Gb (Purple)",
    "tag": "discount"
  }
]